{
    "errors": [
        [
            "",
            ""
        ],
        [
            "ServerTimeout",
            ""
        ],
        [
            "ServerTimeout",
            ""
        ],
        [
            "ServerTimeout",
            ""
        ],
        [
            "ServerTimeout",
            ""
        ],
        [
            "ServerTimeout",
            ""
        ],
        [
            "ServerTimeout",
            ""
        ],
        [
            "ServerTimeout",
            ""
        ],
        [
            "",
            ""
        ],
        [
            "",
            ""
        ],
        [
            "",
            ""
        ],
        [
            "",
            ""
        ],
        [
            "",
            ""
        ],
        [
            "",
            ""
        ],
        [
            "",
            ""
        ],
        [
            "",
            ""
        ],
        [
            "",
            ""
        ],
        [
            "",
            ""
        ],
        [
            "",
            ""
        ],
        [
            "",
            ""
        ],
        [
            "",
            ""
        ],
        [
            "",
            ""
        ],
        [
            "",
            ""
        ],
        [
            "",
            ""
        ],
        [
            "",
            ""
        ],
        [
            "",
            ""
        ],
        [
            "",
            ""
        ],
        [
            "",
            ""
        ],
        [
            "",
            ""
        ],
        [
            "",
            ""
        ],
        [
            "",
            ""
        ]
    ],
    "gameMetaURL": "http://games.ggp.org/base/games/nineBoardTicTacToe/v0/",
    "goalValues": [
        0,
        100
    ],
    "isAborted": false,
    "isCompleted": true,
    "matchId": "nineBoardTicTacToe-MiniMaxRandomPlayer-vs-ConfidencePlayer-20160506_074326.game95",
    "moves": [
        [
            "( play 1 2 1 1 x )",
            "noop"
        ],
        [
            "noop",
            "( play 1 1 3 2 o )"
        ],
        [
            "( play 3 2 2 1 x )",
            "noop"
        ],
        [
            "noop",
            "( play 2 1 1 3 o )"
        ],
        [
            "( play 1 3 3 2 x )",
            "noop"
        ],
        [
            "noop",
            "( play 3 2 3 3 o )"
        ],
        [
            "( play 3 3 2 1 x )",
            "noop"
        ],
        [
            "noop",
            "( play 2 1 2 3 o )"
        ],
        [
            "( play 2 3 1 3 x )",
            "noop"
        ],
        [
            "noop",
            "( play 1 3 2 1 o )"
        ],
        [
            "( play 2 1 1 1 x )",
            "noop"
        ],
        [
            "noop",
            "( play 1 1 3 3 o )"
        ],
        [
            "( play 3 3 3 3 x )",
            "noop"
        ],
        [
            "noop",
            "( play 3 3 3 2 o )"
        ],
        [
            "( play 3 2 1 3 x )",
            "noop"
        ],
        [
            "noop",
            "( play 1 3 1 1 o )"
        ],
        [
            "( play 1 1 1 2 x )",
            "noop"
        ],
        [
            "noop",
            "( play 1 2 3 1 o )"
        ],
        [
            "( play 3 1 3 2 x )",
            "noop"
        ],
        [
            "noop",
            "( play 3 2 3 1 o )"
        ],
        [
            "( play 3 1 3 1 x )",
            "noop"
        ],
        [
            "noop",
            "( play 3 1 2 2 o )"
        ],
        [
            "( play 2 2 1 2 x )",
            "noop"
        ],
        [
            "noop",
            "( play 1 2 2 2 o )"
        ],
        [
            "( play 2 2 3 3 x )",
            "noop"
        ],
        [
            "noop",
            "( play 3 3 1 2 o )"
        ],
        [
            "( play 1 2 2 3 x )",
            "noop"
        ],
        [
            "noop",
            "( play 2 3 1 2 o )"
        ],
        [
            "( play 1 2 1 3 x )",
            "noop"
        ],
        [
            "noop",
            "( play 1 3 3 1 o )"
        ]
    ],
    "playClock": 10,
    "playerNamesFromHost": [
        "MiniMaxRandomPlayer",
        "ConfidencePlayer"
    ],
    "previewClock": -1,
    "randomToken": "Bp6mF1JgBwCg8rcVcFqDcVEA1Nlmk8vA",
    "scrambled": false,
    "startClock": 30,
    "startTime": 1462575648687,
    "stateTimes": [
        1462575648690,
        1462575659988,
        1462575671003,
        1462575682015,
        1462575693026,
        1462575704035,
        1462575715051,
        1462575726064,
        1462575735272,
        1462575744474,
        1462575753786,
        1462575762965,
        1462575772139,
        1462575781280,
        1462575790461,
        1462575799648,
        1462575808804,
        1462575817892,
        1462575826964,
        1462575836106,
        1462575845192,
        1462575854398,
        1462575863595,
        1462575872748,
        1462575881848,
        1462575891008,
        1462575900117,
        1462575909205,
        1462575918308,
        1462575927326,
        1462575936344
    ],
    "states": [
        "( ( control xPlayer ) )",
        "( ( control oPlayer ) ( currentBoard 1 1 ) ( mark 1 2 1 1 x ) )",
        "( ( control xPlayer ) ( currentBoard 3 2 ) ( mark 1 1 3 2 o ) ( mark 1 2 1 1 x ) )",
        "( ( control oPlayer ) ( mark 3 2 2 1 x ) ( mark 1 1 3 2 o ) ( mark 1 2 1 1 x ) ( currentBoard 2 1 ) )",
        "( ( control xPlayer ) ( currentBoard 1 3 ) ( mark 3 2 2 1 x ) ( mark 1 1 3 2 o ) ( mark 2 1 1 3 o ) ( mark 1 2 1 1 x ) )",
        "( ( control oPlayer ) ( mark 1 3 3 2 x ) ( currentBoard 3 2 ) ( mark 3 2 2 1 x ) ( mark 1 1 3 2 o ) ( mark 2 1 1 3 o ) ( mark 1 2 1 1 x ) )",
        "( ( control xPlayer ) ( mark 3 2 3 3 o ) ( mark 1 3 3 2 x ) ( mark 3 2 2 1 x ) ( mark 1 1 3 2 o ) ( mark 2 1 1 3 o ) ( currentBoard 3 3 ) ( mark 1 2 1 1 x ) )",
        "( ( control oPlayer ) ( mark 3 3 2 1 x ) ( mark 3 2 3 3 o ) ( mark 1 3 3 2 x ) ( mark 3 2 2 1 x ) ( mark 1 1 3 2 o ) ( mark 2 1 1 3 o ) ( mark 1 2 1 1 x ) ( currentBoard 2 1 ) )",
        "( ( control xPlayer ) ( currentBoard 2 3 ) ( mark 3 3 2 1 x ) ( mark 3 2 3 3 o ) ( mark 1 3 3 2 x ) ( mark 2 1 2 3 o ) ( mark 3 2 2 1 x ) ( mark 1 1 3 2 o ) ( mark 2 1 1 3 o ) ( mark 1 2 1 1 x ) )",
        "( ( control oPlayer ) ( mark 3 3 2 1 x ) ( currentBoard 1 3 ) ( mark 3 2 3 3 o ) ( mark 1 3 3 2 x ) ( mark 2 3 1 3 x ) ( mark 2 1 2 3 o ) ( mark 3 2 2 1 x ) ( mark 1 1 3 2 o ) ( mark 2 1 1 3 o ) ( mark 1 2 1 1 x ) )",
        "( ( control xPlayer ) ( mark 3 3 2 1 x ) ( mark 3 2 3 3 o ) ( mark 1 3 3 2 x ) ( mark 2 3 1 3 x ) ( mark 2 1 2 3 o ) ( mark 3 2 2 1 x ) ( mark 1 1 3 2 o ) ( mark 2 1 1 3 o ) ( mark 1 3 2 1 o ) ( mark 1 2 1 1 x ) ( currentBoard 2 1 ) )",
        "( ( control oPlayer ) ( mark 3 3 2 1 x ) ( mark 1 3 3 2 x ) ( mark 2 3 1 3 x ) ( mark 2 1 1 3 o ) ( mark 1 1 3 2 o ) ( mark 1 3 2 1 o ) ( mark 1 2 1 1 x ) ( mark 2 1 1 1 x ) ( mark 3 2 3 3 o ) ( currentBoard 1 1 ) ( mark 2 1 2 3 o ) ( mark 3 2 2 1 x ) )",
        "( ( control xPlayer ) ( mark 3 3 2 1 x ) ( mark 1 3 3 2 x ) ( mark 2 3 1 3 x ) ( mark 2 1 1 3 o ) ( mark 1 1 3 2 o ) ( mark 1 3 2 1 o ) ( mark 1 2 1 1 x ) ( mark 2 1 1 1 x ) ( mark 3 2 3 3 o ) ( mark 2 1 2 3 o ) ( mark 1 1 3 3 o ) ( mark 3 2 2 1 x ) ( currentBoard 3 3 ) )",
        "( ( control oPlayer ) ( mark 3 3 2 1 x ) ( mark 1 3 3 2 x ) ( mark 2 3 1 3 x ) ( mark 2 1 1 3 o ) ( mark 1 1 3 2 o ) ( mark 1 3 2 1 o ) ( mark 1 2 1 1 x ) ( mark 2 1 1 1 x ) ( mark 3 3 3 3 x ) ( mark 3 2 3 3 o ) ( mark 2 1 2 3 o ) ( mark 1 1 3 3 o ) ( mark 3 2 2 1 x ) ( currentBoard 3 3 ) )",
        "( ( control xPlayer ) ( mark 3 3 2 1 x ) ( mark 1 3 3 2 x ) ( mark 2 3 1 3 x ) ( currentBoard 3 2 ) ( mark 2 1 1 3 o ) ( mark 1 1 3 2 o ) ( mark 1 3 2 1 o ) ( mark 1 2 1 1 x ) ( mark 3 3 3 2 o ) ( mark 2 1 1 1 x ) ( mark 3 3 3 3 x ) ( mark 3 2 3 3 o ) ( mark 2 1 2 3 o ) ( mark 1 1 3 3 o ) ( mark 3 2 2 1 x ) )",
        "( ( mark 3 2 1 3 x ) ( control oPlayer ) ( mark 3 3 2 1 x ) ( mark 1 3 3 2 x ) ( mark 2 3 1 3 x ) ( mark 2 1 1 3 o ) ( mark 1 1 3 2 o ) ( mark 1 3 2 1 o ) ( mark 1 2 1 1 x ) ( mark 3 3 3 2 o ) ( mark 2 1 1 1 x ) ( mark 3 3 3 3 x ) ( currentBoard 1 3 ) ( mark 3 2 3 3 o ) ( mark 2 1 2 3 o ) ( mark 1 1 3 3 o ) ( mark 3 2 2 1 x ) )",
        "( ( control xPlayer ) ( mark 1 3 1 1 o ) ( mark 3 2 1 3 x ) ( mark 3 3 2 1 x ) ( mark 1 3 3 2 x ) ( mark 2 3 1 3 x ) ( mark 2 1 1 3 o ) ( mark 1 1 3 2 o ) ( mark 1 3 2 1 o ) ( mark 1 2 1 1 x ) ( mark 3 3 3 2 o ) ( mark 2 1 1 1 x ) ( mark 3 3 3 3 x ) ( mark 3 2 3 3 o ) ( currentBoard 1 1 ) ( mark 2 1 2 3 o ) ( mark 1 1 3 3 o ) ( mark 3 2 2 1 x ) )",
        "( ( mark 1 3 1 1 o ) ( mark 3 2 1 3 x ) ( control oPlayer ) ( mark 3 3 2 1 x ) ( mark 1 3 3 2 x ) ( currentBoard 1 2 ) ( mark 2 3 1 3 x ) ( mark 2 1 1 3 o ) ( mark 1 1 3 2 o ) ( mark 1 3 2 1 o ) ( mark 1 1 1 2 x ) ( mark 1 2 1 1 x ) ( mark 3 3 3 2 o ) ( mark 2 1 1 1 x ) ( mark 3 3 3 3 x ) ( mark 3 2 3 3 o ) ( mark 2 1 2 3 o ) ( mark 1 1 3 3 o ) ( mark 3 2 2 1 x ) )",
        "( ( control xPlayer ) ( mark 1 3 1 1 o ) ( mark 3 2 1 3 x ) ( mark 3 3 2 1 x ) ( currentBoard 3 1 ) ( mark 1 3 3 2 x ) ( mark 2 3 1 3 x ) ( mark 2 1 1 3 o ) ( mark 1 1 3 2 o ) ( mark 1 3 2 1 o ) ( mark 1 1 1 2 x ) ( mark 1 2 3 1 o ) ( mark 1 2 1 1 x ) ( mark 3 3 3 2 o ) ( mark 2 1 1 1 x ) ( mark 3 3 3 3 x ) ( mark 3 2 3 3 o ) ( mark 2 1 2 3 o ) ( mark 1 1 3 3 o ) ( mark 3 2 2 1 x ) )",
        "( ( mark 1 3 1 1 o ) ( mark 3 2 1 3 x ) ( control oPlayer ) ( mark 3 3 2 1 x ) ( mark 3 1 3 2 x ) ( mark 1 3 3 2 x ) ( mark 2 3 1 3 x ) ( currentBoard 3 2 ) ( mark 2 1 1 3 o ) ( mark 1 1 3 2 o ) ( mark 1 3 2 1 o ) ( mark 1 1 1 2 x ) ( mark 1 2 3 1 o ) ( mark 1 2 1 1 x ) ( mark 3 3 3 2 o ) ( mark 2 1 1 1 x ) ( mark 3 3 3 3 x ) ( mark 3 2 3 3 o ) ( mark 2 1 2 3 o ) ( mark 1 1 3 3 o ) ( mark 3 2 2 1 x ) )",
        "( ( control xPlayer ) ( mark 1 3 1 1 o ) ( mark 3 2 1 3 x ) ( mark 3 3 2 1 x ) ( mark 3 1 3 2 x ) ( currentBoard 3 1 ) ( mark 1 3 3 2 x ) ( mark 2 3 1 3 x ) ( mark 2 1 1 3 o ) ( mark 1 1 3 2 o ) ( mark 1 3 2 1 o ) ( mark 1 1 1 2 x ) ( mark 1 2 3 1 o ) ( mark 1 2 1 1 x ) ( mark 3 3 3 2 o ) ( mark 2 1 1 1 x ) ( mark 3 3 3 3 x ) ( mark 3 2 3 3 o ) ( mark 3 2 3 1 o ) ( mark 2 1 2 3 o ) ( mark 1 1 3 3 o ) ( mark 3 2 2 1 x ) )",
        "( ( mark 1 3 1 1 o ) ( mark 3 2 1 3 x ) ( control oPlayer ) ( mark 3 3 2 1 x ) ( mark 3 1 3 2 x ) ( currentBoard 3 1 ) ( mark 1 3 3 2 x ) ( mark 2 3 1 3 x ) ( mark 2 1 1 3 o ) ( mark 1 1 3 2 o ) ( mark 1 3 2 1 o ) ( mark 1 1 1 2 x ) ( mark 1 2 3 1 o ) ( mark 1 2 1 1 x ) ( mark 3 3 3 2 o ) ( mark 2 1 1 1 x ) ( mark 3 3 3 3 x ) ( mark 3 2 3 3 o ) ( mark 3 2 3 1 o ) ( mark 2 1 2 3 o ) ( mark 1 1 3 3 o ) ( mark 3 2 2 1 x ) ( mark 3 1 3 1 x ) )",
        "( ( control xPlayer ) ( mark 1 3 1 1 o ) ( mark 3 2 1 3 x ) ( mark 3 3 2 1 x ) ( mark 3 1 3 2 x ) ( mark 3 1 2 2 o ) ( mark 1 3 3 2 x ) ( mark 2 3 1 3 x ) ( mark 2 1 1 3 o ) ( mark 1 1 3 2 o ) ( mark 1 3 2 1 o ) ( mark 1 1 1 2 x ) ( currentBoard 2 2 ) ( mark 1 2 3 1 o ) ( mark 1 2 1 1 x ) ( mark 3 3 3 2 o ) ( mark 2 1 1 1 x ) ( mark 3 3 3 3 x ) ( mark 3 2 3 3 o ) ( mark 3 2 3 1 o ) ( mark 2 1 2 3 o ) ( mark 1 1 3 3 o ) ( mark 3 2 2 1 x ) ( mark 3 1 3 1 x ) )",
        "( ( mark 1 3 1 1 o ) ( mark 3 3 2 1 x ) ( currentBoard 1 2 ) ( mark 2 3 1 3 x ) ( mark 2 1 1 3 o ) ( mark 1 3 2 1 o ) ( mark 2 1 2 3 o ) ( mark 1 1 3 3 o ) ( mark 3 1 3 1 x ) ( mark 2 2 1 2 x ) ( mark 3 2 1 3 x ) ( control oPlayer ) ( mark 3 1 3 2 x ) ( mark 3 1 2 2 o ) ( mark 1 3 3 2 x ) ( mark 1 1 3 2 o ) ( mark 1 1 1 2 x ) ( mark 1 2 3 1 o ) ( mark 1 2 1 1 x ) ( mark 3 3 3 2 o ) ( mark 2 1 1 1 x ) ( mark 3 3 3 3 x ) ( mark 3 2 3 3 o ) ( mark 3 2 3 1 o ) ( mark 3 2 2 1 x ) )",
        "( ( mark 1 3 1 1 o ) ( mark 3 3 2 1 x ) ( mark 2 3 1 3 x ) ( mark 1 2 2 2 o ) ( mark 2 1 1 3 o ) ( mark 1 3 2 1 o ) ( mark 2 1 2 3 o ) ( mark 1 1 3 3 o ) ( mark 3 1 3 1 x ) ( mark 2 2 1 2 x ) ( control xPlayer ) ( mark 3 2 1 3 x ) ( mark 3 1 3 2 x ) ( mark 3 1 2 2 o ) ( mark 1 3 3 2 x ) ( mark 1 1 3 2 o ) ( mark 1 1 1 2 x ) ( mark 1 2 3 1 o ) ( currentBoard 2 2 ) ( mark 1 2 1 1 x ) ( mark 3 3 3 2 o ) ( mark 2 1 1 1 x ) ( mark 3 3 3 3 x ) ( mark 3 2 3 3 o ) ( mark 3 2 3 1 o ) ( mark 3 2 2 1 x ) )",
        "( ( mark 1 3 1 1 o ) ( mark 3 3 2 1 x ) ( mark 2 3 1 3 x ) ( mark 1 2 2 2 o ) ( mark 2 1 1 3 o ) ( mark 1 3 2 1 o ) ( mark 2 1 2 3 o ) ( mark 1 1 3 3 o ) ( mark 3 1 3 1 x ) ( mark 2 2 1 2 x ) ( mark 3 2 1 3 x ) ( control oPlayer ) ( mark 3 1 3 2 x ) ( mark 3 1 2 2 o ) ( mark 1 3 3 2 x ) ( mark 2 2 3 3 x ) ( mark 1 1 3 2 o ) ( mark 1 1 1 2 x ) ( mark 1 2 3 1 o ) ( mark 1 2 1 1 x ) ( mark 3 3 3 2 o ) ( mark 2 1 1 1 x ) ( mark 3 3 3 3 x ) ( mark 3 2 3 3 o ) ( mark 3 2 3 1 o ) ( mark 3 2 2 1 x ) ( currentBoard 3 3 ) )",
        "( ( mark 1 3 1 1 o ) ( mark 3 3 2 1 x ) ( currentBoard 1 2 ) ( mark 2 3 1 3 x ) ( mark 1 2 2 2 o ) ( mark 2 1 1 3 o ) ( mark 1 3 2 1 o ) ( mark 2 1 2 3 o ) ( mark 1 1 3 3 o ) ( mark 3 1 3 1 x ) ( mark 2 2 1 2 x ) ( control xPlayer ) ( mark 3 2 1 3 x ) ( mark 3 1 3 2 x ) ( mark 3 1 2 2 o ) ( mark 1 3 3 2 x ) ( mark 2 2 3 3 x ) ( mark 1 1 3 2 o ) ( mark 1 1 1 2 x ) ( mark 1 2 3 1 o ) ( mark 1 2 1 1 x ) ( mark 3 3 3 2 o ) ( mark 2 1 1 1 x ) ( mark 3 3 3 3 x ) ( mark 3 2 3 3 o ) ( mark 3 2 3 1 o ) ( mark 3 2 2 1 x ) ( mark 3 3 1 2 o ) )",
        "( ( mark 1 3 1 1 o ) ( mark 3 3 2 1 x ) ( mark 2 3 1 3 x ) ( mark 1 2 2 2 o ) ( mark 2 1 1 3 o ) ( mark 1 3 2 1 o ) ( currentBoard 2 3 ) ( mark 2 1 2 3 o ) ( mark 1 1 3 3 o ) ( mark 3 1 3 1 x ) ( mark 2 2 1 2 x ) ( mark 1 2 2 3 x ) ( mark 3 2 1 3 x ) ( control oPlayer ) ( mark 3 1 3 2 x ) ( mark 3 1 2 2 o ) ( mark 1 3 3 2 x ) ( mark 2 2 3 3 x ) ( mark 1 1 3 2 o ) ( mark 1 1 1 2 x ) ( mark 1 2 3 1 o ) ( mark 1 2 1 1 x ) ( mark 3 3 3 2 o ) ( mark 2 1 1 1 x ) ( mark 3 3 3 3 x ) ( mark 3 2 3 3 o ) ( mark 3 2 3 1 o ) ( mark 3 2 2 1 x ) ( mark 3 3 1 2 o ) )",
        "( ( mark 1 3 1 1 o ) ( mark 3 3 2 1 x ) ( currentBoard 1 2 ) ( mark 2 3 1 3 x ) ( mark 1 2 2 2 o ) ( mark 2 1 1 3 o ) ( mark 1 3 2 1 o ) ( mark 2 1 2 3 o ) ( mark 1 1 3 3 o ) ( mark 3 1 3 1 x ) ( mark 2 2 1 2 x ) ( mark 1 2 2 3 x ) ( control xPlayer ) ( mark 3 2 1 3 x ) ( mark 3 1 3 2 x ) ( mark 3 1 2 2 o ) ( mark 1 3 3 2 x ) ( mark 2 3 1 2 o ) ( mark 2 2 3 3 x ) ( mark 1 1 3 2 o ) ( mark 1 1 1 2 x ) ( mark 1 2 3 1 o ) ( mark 1 2 1 1 x ) ( mark 3 3 3 2 o ) ( mark 2 1 1 1 x ) ( mark 3 3 3 3 x ) ( mark 3 2 3 3 o ) ( mark 3 2 3 1 o ) ( mark 3 2 2 1 x ) ( mark 3 3 1 2 o ) )",
        "( ( mark 1 3 1 1 o ) ( mark 3 3 2 1 x ) ( mark 2 3 1 3 x ) ( mark 1 2 2 2 o ) ( mark 2 1 1 3 o ) ( mark 1 3 2 1 o ) ( mark 2 1 2 3 o ) ( mark 1 1 3 3 o ) ( mark 3 1 3 1 x ) ( mark 2 2 1 2 x ) ( mark 1 2 2 3 x ) ( mark 3 2 1 3 x ) ( control oPlayer ) ( mark 3 1 3 2 x ) ( mark 3 1 2 2 o ) ( mark 1 3 3 2 x ) ( mark 2 3 1 2 o ) ( mark 2 2 3 3 x ) ( mark 1 1 3 2 o ) ( mark 1 1 1 2 x ) ( mark 1 2 3 1 o ) ( mark 1 2 1 1 x ) ( mark 3 3 3 2 o ) ( mark 2 1 1 1 x ) ( mark 3 3 3 3 x ) ( currentBoard 1 3 ) ( mark 3 2 3 3 o ) ( mark 3 2 3 1 o ) ( mark 3 2 2 1 x ) ( mark 3 3 1 2 o ) ( mark 1 2 1 3 x ) )",
        "( ( mark 1 3 1 1 o ) ( mark 3 3 2 1 x ) ( currentBoard 3 1 ) ( mark 2 3 1 3 x ) ( mark 1 3 3 1 o ) ( mark 1 2 2 2 o ) ( mark 2 1 1 3 o ) ( mark 1 3 2 1 o ) ( mark 2 1 2 3 o ) ( mark 1 1 3 3 o ) ( mark 3 1 3 1 x ) ( mark 2 2 1 2 x ) ( mark 1 2 2 3 x ) ( control xPlayer ) ( mark 3 2 1 3 x ) ( mark 3 1 3 2 x ) ( mark 3 1 2 2 o ) ( mark 1 3 3 2 x ) ( mark 2 3 1 2 o ) ( mark 2 2 3 3 x ) ( mark 1 1 3 2 o ) ( mark 1 1 1 2 x ) ( mark 1 2 3 1 o ) ( mark 1 2 1 1 x ) ( mark 3 3 3 2 o ) ( mark 2 1 1 1 x ) ( mark 3 3 3 3 x ) ( mark 3 2 3 3 o ) ( mark 3 2 3 1 o ) ( mark 3 2 2 1 x ) ( mark 3 3 1 2 o ) ( mark 1 2 1 3 x ) )"
    ],
    "tournamentNameFromHost": ""
}