{
    "errors": [
        [
            "",
            ""
        ],
        [
            "",
            ""
        ],
        [
            "",
            ""
        ],
        [
            "",
            ""
        ],
        [
            "",
            ""
        ],
        [
            "",
            ""
        ],
        [
            "",
            ""
        ],
        [
            "",
            ""
        ],
        [
            "",
            ""
        ],
        [
            "",
            ""
        ],
        [
            "",
            ""
        ],
        [
            "",
            ""
        ],
        [
            "",
            ""
        ],
        [
            "",
            ""
        ],
        [
            "",
            ""
        ],
        [
            "",
            ""
        ],
        [
            "",
            ""
        ],
        [
            "",
            ""
        ],
        [
            "",
            ""
        ],
        [
            "",
            ""
        ],
        [
            "",
            ""
        ],
        [
            "",
            ""
        ],
        [
            "",
            ""
        ],
        [
            "",
            ""
        ],
        [
            "",
            ""
        ],
        [
            "",
            ""
        ],
        [
            "",
            ""
        ],
        [
            "",
            ""
        ],
        [
            "",
            ""
        ],
        [
            "",
            ""
        ],
        [
            "",
            ""
        ],
        [
            "",
            ""
        ],
        [
            "",
            ""
        ]
    ],
    "gameMetaURL": "http://games.ggp.org/base/games/nineBoardTicTacToe/v0/",
    "goalValues": [
        0,
        100
    ],
    "isAborted": false,
    "isCompleted": true,
    "matchId": "nineBoardTicTacToe-LearningPlayer-vs-MultithreadedUCTPlayer-20160506_192409.game90",
    "moves": [
        [
            "( play 1 2 2 2 x )",
            "noop"
        ],
        [
            "noop",
            "( play 2 2 2 2 o )"
        ],
        [
            "( play 2 2 3 1 x )",
            "noop"
        ],
        [
            "noop",
            "( play 3 1 1 2 o )"
        ],
        [
            "( play 1 2 3 2 x )",
            "noop"
        ],
        [
            "noop",
            "( play 3 2 2 2 o )"
        ],
        [
            "( play 2 2 3 3 x )",
            "noop"
        ],
        [
            "noop",
            "( play 3 3 3 2 o )"
        ],
        [
            "( play 3 2 3 2 x )",
            "noop"
        ],
        [
            "noop",
            "( play 3 2 1 1 o )"
        ],
        [
            "( play 1 1 2 3 x )",
            "noop"
        ],
        [
            "noop",
            "( play 2 3 3 2 o )"
        ],
        [
            "( play 3 2 3 3 x )",
            "noop"
        ],
        [
            "noop",
            "( play 3 3 1 1 o )"
        ],
        [
            "( play 1 1 1 3 x )",
            "noop"
        ],
        [
            "noop",
            "( play 1 3 1 3 o )"
        ],
        [
            "( play 1 3 2 3 x )",
            "noop"
        ],
        [
            "noop",
            "( play 2 3 1 3 o )"
        ],
        [
            "( play 1 3 1 1 x )",
            "noop"
        ],
        [
            "noop",
            "( play 1 1 3 1 o )"
        ],
        [
            "( play 3 1 2 1 x )",
            "noop"
        ],
        [
            "noop",
            "( play 2 1 1 3 o )"
        ],
        [
            "( play 1 3 2 2 x )",
            "noop"
        ],
        [
            "noop",
            "( play 2 2 2 1 o )"
        ],
        [
            "( play 2 1 3 1 x )",
            "noop"
        ],
        [
            "noop",
            "( play 3 1 3 1 o )"
        ],
        [
            "( play 3 1 2 3 x )",
            "noop"
        ],
        [
            "noop",
            "( play 2 3 2 1 o )"
        ],
        [
            "( play 2 1 1 1 x )",
            "noop"
        ],
        [
            "noop",
            "( play 1 1 3 3 o )"
        ],
        [
            "( play 3 3 2 2 x )",
            "noop"
        ],
        [
            "noop",
            "( play 2 2 2 3 o )"
        ]
    ],
    "playClock": 10,
    "playerNamesFromHost": [
        "MultithreadedUCTPlayer",
        "LearningPlayer"
    ],
    "previewClock": -1,
    "randomToken": "2sP8YK6GT4Vk3aiYnM8Rwyvmzmkhg67D",
    "scrambled": false,
    "startClock": 30,
    "startTime": 1462607672557,
    "stateTimes": [
        1462607672561,
        1462607682054,
        1462607691304,
        1462607700543,
        1462607709707,
        1462607718838,
        1462607727886,
        1462607737065,
        1462607746206,
        1462607755440,
        1462607764645,
        1462607773786,
        1462607783146,
        1462607792348,
        1462607801490,
        1462607810640,
        1462607819767,
        1462607828983,
        1462607838148,
        1462607847361,
        1462607856427,
        1462607865579,
        1462607874741,
        1462607883919,
        1462607893006,
        1462607902128,
        1462607911241,
        1462607920370,
        1462607929490,
        1462607938584,
        1462607947620,
        1462607956743,
        1462607965774
    ],
    "states": [
        "( ( control xPlayer ) )",
        "( ( control oPlayer ) ( mark 1 2 2 2 x ) ( currentBoard 2 2 ) )",
        "( ( control xPlayer ) ( mark 2 2 2 2 o ) ( mark 1 2 2 2 x ) ( currentBoard 2 2 ) )",
        "( ( control oPlayer ) ( currentBoard 3 1 ) ( mark 2 2 2 2 o ) ( mark 1 2 2 2 x ) ( mark 2 2 3 1 x ) )",
        "( ( control xPlayer ) ( currentBoard 1 2 ) ( mark 2 2 2 2 o ) ( mark 1 2 2 2 x ) ( mark 2 2 3 1 x ) ( mark 3 1 1 2 o ) )",
        "( ( control oPlayer ) ( mark 2 2 2 2 o ) ( currentBoard 3 2 ) ( mark 1 2 2 2 x ) ( mark 2 2 3 1 x ) ( mark 1 2 3 2 x ) ( mark 3 1 1 2 o ) )",
        "( ( control xPlayer ) ( mark 2 2 2 2 o ) ( mark 3 2 2 2 o ) ( mark 1 2 2 2 x ) ( currentBoard 2 2 ) ( mark 2 2 3 1 x ) ( mark 1 2 3 2 x ) ( mark 3 1 1 2 o ) )",
        "( ( control oPlayer ) ( mark 2 2 2 2 o ) ( mark 2 2 3 3 x ) ( mark 3 2 2 2 o ) ( currentBoard 3 3 ) ( mark 1 2 2 2 x ) ( mark 2 2 3 1 x ) ( mark 1 2 3 2 x ) ( mark 3 1 1 2 o ) )",
        "( ( mark 3 3 3 2 o ) ( control xPlayer ) ( mark 2 2 2 2 o ) ( currentBoard 3 2 ) ( mark 2 2 3 3 x ) ( mark 3 2 2 2 o ) ( mark 1 2 2 2 x ) ( mark 2 2 3 1 x ) ( mark 1 2 3 2 x ) ( mark 3 1 1 2 o ) )",
        "( ( mark 3 3 3 2 o ) ( control oPlayer ) ( mark 3 2 3 2 x ) ( mark 2 2 2 2 o ) ( currentBoard 3 2 ) ( mark 2 2 3 3 x ) ( mark 3 2 2 2 o ) ( mark 1 2 2 2 x ) ( mark 2 2 3 1 x ) ( mark 1 2 3 2 x ) ( mark 3 1 1 2 o ) )",
        "( ( mark 3 3 3 2 o ) ( control xPlayer ) ( mark 3 2 3 2 x ) ( currentBoard 1 1 ) ( mark 2 2 2 2 o ) ( mark 2 2 3 3 x ) ( mark 3 2 2 2 o ) ( mark 1 2 2 2 x ) ( mark 2 2 3 1 x ) ( mark 1 2 3 2 x ) ( mark 3 1 1 2 o ) ( mark 3 2 1 1 o ) )",
        "( ( control oPlayer ) ( mark 3 2 3 2 x ) ( mark 2 2 2 2 o ) ( mark 2 2 3 3 x ) ( mark 3 1 1 2 o ) ( mark 3 2 1 1 o ) ( currentBoard 2 3 ) ( mark 3 3 3 2 o ) ( mark 3 2 2 2 o ) ( mark 1 2 2 2 x ) ( mark 1 1 2 3 x ) ( mark 2 2 3 1 x ) ( mark 1 2 3 2 x ) )",
        "( ( control xPlayer ) ( mark 3 2 3 2 x ) ( mark 2 2 2 2 o ) ( currentBoard 3 2 ) ( mark 2 2 3 3 x ) ( mark 3 1 1 2 o ) ( mark 3 2 1 1 o ) ( mark 3 3 3 2 o ) ( mark 2 3 3 2 o ) ( mark 3 2 2 2 o ) ( mark 1 2 2 2 x ) ( mark 1 1 2 3 x ) ( mark 2 2 3 1 x ) ( mark 1 2 3 2 x ) )",
        "( ( control oPlayer ) ( mark 3 2 3 2 x ) ( mark 2 2 2 2 o ) ( mark 3 2 3 3 x ) ( mark 2 2 3 3 x ) ( mark 3 1 1 2 o ) ( mark 3 2 1 1 o ) ( mark 3 3 3 2 o ) ( mark 2 3 3 2 o ) ( mark 3 2 2 2 o ) ( mark 1 2 2 2 x ) ( currentBoard 3 3 ) ( mark 1 1 2 3 x ) ( mark 2 2 3 1 x ) ( mark 1 2 3 2 x ) )",
        "( ( control xPlayer ) ( mark 3 3 1 1 o ) ( mark 3 2 3 2 x ) ( mark 2 2 2 2 o ) ( mark 3 2 3 3 x ) ( mark 2 2 3 3 x ) ( mark 3 1 1 2 o ) ( mark 3 2 1 1 o ) ( mark 3 3 3 2 o ) ( mark 2 3 3 2 o ) ( currentBoard 1 1 ) ( mark 3 2 2 2 o ) ( mark 1 2 2 2 x ) ( mark 1 1 2 3 x ) ( mark 2 2 3 1 x ) ( mark 1 2 3 2 x ) )",
        "( ( control oPlayer ) ( mark 3 3 1 1 o ) ( mark 3 2 3 2 x ) ( mark 2 2 2 2 o ) ( mark 1 1 1 3 x ) ( mark 3 2 3 3 x ) ( mark 2 2 3 3 x ) ( mark 3 1 1 2 o ) ( mark 3 2 1 1 o ) ( mark 3 3 3 2 o ) ( mark 2 3 3 2 o ) ( currentBoard 1 3 ) ( mark 3 2 2 2 o ) ( mark 1 2 2 2 x ) ( mark 1 1 2 3 x ) ( mark 2 2 3 1 x ) ( mark 1 2 3 2 x ) )",
        "( ( control xPlayer ) ( mark 3 3 1 1 o ) ( mark 3 2 3 2 x ) ( mark 2 2 2 2 o ) ( mark 1 1 1 3 x ) ( mark 3 2 3 3 x ) ( mark 2 2 3 3 x ) ( mark 3 1 1 2 o ) ( mark 3 2 1 1 o ) ( mark 3 3 3 2 o ) ( mark 2 3 3 2 o ) ( currentBoard 1 3 ) ( mark 3 2 2 2 o ) ( mark 1 3 1 3 o ) ( mark 1 2 2 2 x ) ( mark 1 1 2 3 x ) ( mark 2 2 3 1 x ) ( mark 1 2 3 2 x ) )",
        "( ( control oPlayer ) ( mark 3 3 1 1 o ) ( mark 1 3 2 3 x ) ( mark 3 2 3 2 x ) ( mark 2 2 2 2 o ) ( mark 1 1 1 3 x ) ( mark 3 2 3 3 x ) ( mark 2 2 3 3 x ) ( mark 3 1 1 2 o ) ( mark 3 2 1 1 o ) ( currentBoard 2 3 ) ( mark 3 3 3 2 o ) ( mark 2 3 3 2 o ) ( mark 3 2 2 2 o ) ( mark 1 3 1 3 o ) ( mark 1 2 2 2 x ) ( mark 1 1 2 3 x ) ( mark 2 2 3 1 x ) ( mark 1 2 3 2 x ) )",
        "( ( control xPlayer ) ( mark 3 3 1 1 o ) ( mark 1 3 2 3 x ) ( mark 3 2 3 2 x ) ( mark 2 2 2 2 o ) ( mark 1 1 1 3 x ) ( mark 3 2 3 3 x ) ( mark 2 2 3 3 x ) ( mark 3 1 1 2 o ) ( mark 3 2 1 1 o ) ( mark 3 3 3 2 o ) ( mark 2 3 3 2 o ) ( currentBoard 1 3 ) ( mark 3 2 2 2 o ) ( mark 1 3 1 3 o ) ( mark 1 2 2 2 x ) ( mark 1 1 2 3 x ) ( mark 2 2 3 1 x ) ( mark 1 2 3 2 x ) ( mark 2 3 1 3 o ) )",
        "( ( control oPlayer ) ( mark 3 3 1 1 o ) ( mark 1 3 2 3 x ) ( mark 3 2 3 2 x ) ( mark 2 2 2 2 o ) ( mark 1 1 1 3 x ) ( mark 3 2 3 3 x ) ( mark 2 2 3 3 x ) ( mark 1 3 1 1 x ) ( mark 3 1 1 2 o ) ( mark 3 2 1 1 o ) ( mark 3 3 3 2 o ) ( mark 2 3 3 2 o ) ( currentBoard 1 1 ) ( mark 3 2 2 2 o ) ( mark 1 3 1 3 o ) ( mark 1 2 2 2 x ) ( mark 1 1 2 3 x ) ( mark 2 2 3 1 x ) ( mark 1 2 3 2 x ) ( mark 2 3 1 3 o ) )",
        "( ( control xPlayer ) ( mark 1 1 3 1 o ) ( mark 3 3 1 1 o ) ( mark 1 3 2 3 x ) ( currentBoard 3 1 ) ( mark 3 2 3 2 x ) ( mark 2 2 2 2 o ) ( mark 1 1 1 3 x ) ( mark 3 2 3 3 x ) ( mark 2 2 3 3 x ) ( mark 1 3 1 1 x ) ( mark 3 1 1 2 o ) ( mark 3 2 1 1 o ) ( mark 3 3 3 2 o ) ( mark 2 3 3 2 o ) ( mark 3 2 2 2 o ) ( mark 1 3 1 3 o ) ( mark 1 2 2 2 x ) ( mark 1 1 2 3 x ) ( mark 2 2 3 1 x ) ( mark 1 2 3 2 x ) ( mark 2 3 1 3 o ) )",
        "( ( mark 1 1 3 1 o ) ( control oPlayer ) ( mark 3 3 1 1 o ) ( mark 1 3 2 3 x ) ( mark 3 2 3 2 x ) ( mark 2 2 2 2 o ) ( mark 1 1 1 3 x ) ( mark 3 2 3 3 x ) ( mark 2 2 3 3 x ) ( mark 1 3 1 1 x ) ( mark 3 1 1 2 o ) ( mark 3 2 1 1 o ) ( mark 3 3 3 2 o ) ( mark 2 3 3 2 o ) ( mark 3 1 2 1 x ) ( mark 3 2 2 2 o ) ( mark 1 3 1 3 o ) ( mark 1 2 2 2 x ) ( mark 1 1 2 3 x ) ( mark 2 2 3 1 x ) ( mark 1 2 3 2 x ) ( currentBoard 2 1 ) ( mark 2 3 1 3 o ) )",
        "( ( control xPlayer ) ( mark 1 1 3 1 o ) ( mark 3 3 1 1 o ) ( mark 1 3 2 3 x ) ( mark 3 2 3 2 x ) ( mark 2 2 2 2 o ) ( mark 1 1 1 3 x ) ( mark 3 2 3 3 x ) ( mark 2 2 3 3 x ) ( mark 1 3 1 1 x ) ( mark 2 1 1 3 o ) ( mark 3 1 1 2 o ) ( mark 3 2 1 1 o ) ( mark 3 3 3 2 o ) ( mark 2 3 3 2 o ) ( currentBoard 1 3 ) ( mark 3 1 2 1 x ) ( mark 3 2 2 2 o ) ( mark 1 3 1 3 o ) ( mark 1 2 2 2 x ) ( mark 1 1 2 3 x ) ( mark 2 2 3 1 x ) ( mark 1 2 3 2 x ) ( mark 2 3 1 3 o ) )",
        "( ( mark 1 1 3 1 o ) ( mark 3 3 1 1 o ) ( mark 1 3 2 3 x ) ( mark 3 2 3 2 x ) ( mark 2 2 2 2 o ) ( mark 1 1 1 3 x ) ( mark 1 3 1 1 x ) ( mark 2 1 1 3 o ) ( mark 3 1 2 1 x ) ( mark 3 2 2 2 o ) ( mark 1 3 1 3 o ) ( mark 1 2 2 2 x ) ( mark 1 1 2 3 x ) ( mark 1 2 3 2 x ) ( mark 2 3 1 3 o ) ( mark 1 3 2 2 x ) ( control oPlayer ) ( mark 3 2 3 3 x ) ( mark 2 2 3 3 x ) ( currentBoard 2 2 ) ( mark 3 1 1 2 o ) ( mark 3 2 1 1 o ) ( mark 3 3 3 2 o ) ( mark 2 3 3 2 o ) ( mark 2 2 3 1 x ) )",
        "( ( mark 1 1 3 1 o ) ( mark 3 3 1 1 o ) ( mark 1 3 2 3 x ) ( mark 3 2 3 2 x ) ( mark 2 2 2 2 o ) ( mark 1 1 1 3 x ) ( mark 1 3 1 1 x ) ( mark 2 1 1 3 o ) ( mark 3 1 2 1 x ) ( mark 3 2 2 2 o ) ( mark 1 3 1 3 o ) ( mark 1 2 2 2 x ) ( mark 1 1 2 3 x ) ( mark 1 2 3 2 x ) ( mark 2 3 1 3 o ) ( control xPlayer ) ( mark 1 3 2 2 x ) ( mark 3 2 3 3 x ) ( mark 2 2 3 3 x ) ( mark 3 1 1 2 o ) ( mark 2 2 2 1 o ) ( mark 3 2 1 1 o ) ( mark 3 3 3 2 o ) ( mark 2 3 3 2 o ) ( mark 2 2 3 1 x ) ( currentBoard 2 1 ) )",
        "( ( mark 1 1 3 1 o ) ( mark 3 3 1 1 o ) ( mark 1 3 2 3 x ) ( currentBoard 3 1 ) ( mark 3 2 3 2 x ) ( mark 2 2 2 2 o ) ( mark 1 1 1 3 x ) ( mark 1 3 1 1 x ) ( mark 2 1 1 3 o ) ( mark 3 1 2 1 x ) ( mark 2 1 3 1 x ) ( mark 3 2 2 2 o ) ( mark 1 3 1 3 o ) ( mark 1 2 2 2 x ) ( mark 1 1 2 3 x ) ( mark 1 2 3 2 x ) ( mark 2 3 1 3 o ) ( mark 1 3 2 2 x ) ( control oPlayer ) ( mark 3 2 3 3 x ) ( mark 2 2 3 3 x ) ( mark 3 1 1 2 o ) ( mark 2 2 2 1 o ) ( mark 3 2 1 1 o ) ( mark 3 3 3 2 o ) ( mark 2 3 3 2 o ) ( mark 2 2 3 1 x ) )",
        "( ( mark 1 1 3 1 o ) ( mark 3 3 1 1 o ) ( mark 3 1 3 1 o ) ( mark 1 3 2 3 x ) ( currentBoard 3 1 ) ( mark 3 2 3 2 x ) ( mark 2 2 2 2 o ) ( mark 1 1 1 3 x ) ( mark 1 3 1 1 x ) ( mark 2 1 1 3 o ) ( mark 3 1 2 1 x ) ( mark 2 1 3 1 x ) ( mark 3 2 2 2 o ) ( mark 1 3 1 3 o ) ( mark 1 2 2 2 x ) ( mark 1 1 2 3 x ) ( mark 1 2 3 2 x ) ( mark 2 3 1 3 o ) ( control xPlayer ) ( mark 1 3 2 2 x ) ( mark 3 2 3 3 x ) ( mark 2 2 3 3 x ) ( mark 3 1 1 2 o ) ( mark 2 2 2 1 o ) ( mark 3 2 1 1 o ) ( mark 3 3 3 2 o ) ( mark 2 3 3 2 o ) ( mark 2 2 3 1 x ) )",
        "( ( mark 1 1 3 1 o ) ( mark 3 1 2 3 x ) ( mark 3 3 1 1 o ) ( mark 3 1 3 1 o ) ( mark 1 3 2 3 x ) ( mark 3 2 3 2 x ) ( mark 2 2 2 2 o ) ( mark 1 1 1 3 x ) ( mark 1 3 1 1 x ) ( mark 2 1 1 3 o ) ( currentBoard 2 3 ) ( mark 3 1 2 1 x ) ( mark 2 1 3 1 x ) ( mark 3 2 2 2 o ) ( mark 1 3 1 3 o ) ( mark 1 2 2 2 x ) ( mark 1 1 2 3 x ) ( mark 1 2 3 2 x ) ( mark 2 3 1 3 o ) ( mark 1 3 2 2 x ) ( control oPlayer ) ( mark 3 2 3 3 x ) ( mark 2 2 3 3 x ) ( mark 3 1 1 2 o ) ( mark 2 2 2 1 o ) ( mark 3 2 1 1 o ) ( mark 3 3 3 2 o ) ( mark 2 3 3 2 o ) ( mark 2 2 3 1 x ) )",
        "( ( mark 1 1 3 1 o ) ( mark 3 1 2 3 x ) ( mark 3 3 1 1 o ) ( mark 3 1 3 1 o ) ( mark 1 3 2 3 x ) ( mark 2 3 2 1 o ) ( mark 3 2 3 2 x ) ( mark 2 2 2 2 o ) ( mark 1 1 1 3 x ) ( mark 1 3 1 1 x ) ( mark 2 1 1 3 o ) ( mark 3 1 2 1 x ) ( mark 2 1 3 1 x ) ( mark 3 2 2 2 o ) ( mark 1 3 1 3 o ) ( mark 1 2 2 2 x ) ( mark 1 1 2 3 x ) ( mark 1 2 3 2 x ) ( mark 2 3 1 3 o ) ( control xPlayer ) ( mark 1 3 2 2 x ) ( mark 3 2 3 3 x ) ( mark 2 2 3 3 x ) ( mark 3 1 1 2 o ) ( mark 2 2 2 1 o ) ( mark 3 2 1 1 o ) ( mark 3 3 3 2 o ) ( mark 2 3 3 2 o ) ( mark 2 2 3 1 x ) ( currentBoard 2 1 ) )",
        "( ( mark 1 1 3 1 o ) ( mark 3 1 2 3 x ) ( mark 3 3 1 1 o ) ( mark 3 1 3 1 o ) ( mark 1 3 2 3 x ) ( mark 2 3 2 1 o ) ( mark 3 2 3 2 x ) ( mark 2 2 2 2 o ) ( mark 1 1 1 3 x ) ( mark 1 3 1 1 x ) ( mark 2 1 1 3 o ) ( mark 3 1 2 1 x ) ( currentBoard 1 1 ) ( mark 2 1 3 1 x ) ( mark 3 2 2 2 o ) ( mark 1 3 1 3 o ) ( mark 1 2 2 2 x ) ( mark 1 1 2 3 x ) ( mark 1 2 3 2 x ) ( mark 2 3 1 3 o ) ( mark 1 3 2 2 x ) ( control oPlayer ) ( mark 3 2 3 3 x ) ( mark 2 2 3 3 x ) ( mark 3 1 1 2 o ) ( mark 2 2 2 1 o ) ( mark 3 2 1 1 o ) ( mark 3 3 3 2 o ) ( mark 2 1 1 1 x ) ( mark 2 3 3 2 o ) ( mark 2 2 3 1 x ) )",
        "( ( mark 1 1 3 1 o ) ( mark 3 1 2 3 x ) ( mark 3 3 1 1 o ) ( mark 3 1 3 1 o ) ( mark 1 3 2 3 x ) ( mark 2 3 2 1 o ) ( mark 3 2 3 2 x ) ( mark 2 2 2 2 o ) ( mark 1 1 1 3 x ) ( mark 1 3 1 1 x ) ( mark 2 1 1 3 o ) ( mark 3 1 2 1 x ) ( mark 2 1 3 1 x ) ( mark 1 1 3 3 o ) ( mark 3 2 2 2 o ) ( mark 1 3 1 3 o ) ( mark 1 2 2 2 x ) ( mark 1 1 2 3 x ) ( mark 1 2 3 2 x ) ( mark 2 3 1 3 o ) ( control xPlayer ) ( mark 1 3 2 2 x ) ( mark 3 2 3 3 x ) ( mark 2 2 3 3 x ) ( mark 3 1 1 2 o ) ( mark 2 2 2 1 o ) ( mark 3 2 1 1 o ) ( mark 3 3 3 2 o ) ( mark 2 1 1 1 x ) ( mark 2 3 3 2 o ) ( currentBoard 3 3 ) ( mark 2 2 3 1 x ) )",
        "( ( mark 1 1 3 1 o ) ( mark 3 1 2 3 x ) ( mark 3 3 1 1 o ) ( mark 3 1 3 1 o ) ( mark 1 3 2 3 x ) ( mark 2 3 2 1 o ) ( mark 3 2 3 2 x ) ( mark 2 2 2 2 o ) ( mark 1 1 1 3 x ) ( mark 1 3 1 1 x ) ( mark 2 1 1 3 o ) ( mark 3 1 2 1 x ) ( mark 2 1 3 1 x ) ( mark 1 1 3 3 o ) ( mark 3 2 2 2 o ) ( mark 1 3 1 3 o ) ( mark 1 2 2 2 x ) ( mark 1 1 2 3 x ) ( mark 1 2 3 2 x ) ( mark 2 3 1 3 o ) ( mark 1 3 2 2 x ) ( control oPlayer ) ( mark 3 3 2 2 x ) ( mark 3 2 3 3 x ) ( mark 2 2 3 3 x ) ( currentBoard 2 2 ) ( mark 3 1 1 2 o ) ( mark 2 2 2 1 o ) ( mark 3 2 1 1 o ) ( mark 3 3 3 2 o ) ( mark 2 1 1 1 x ) ( mark 2 3 3 2 o ) ( mark 2 2 3 1 x ) )",
        "( ( mark 1 1 3 1 o ) ( mark 3 1 2 3 x ) ( mark 3 3 1 1 o ) ( mark 3 1 3 1 o ) ( mark 1 3 2 3 x ) ( mark 2 3 2 1 o ) ( mark 3 2 3 2 x ) ( mark 2 2 2 2 o ) ( mark 1 1 1 3 x ) ( mark 1 3 1 1 x ) ( mark 2 1 1 3 o ) ( currentBoard 2 3 ) ( mark 3 1 2 1 x ) ( mark 2 1 3 1 x ) ( mark 1 1 3 3 o ) ( mark 3 2 2 2 o ) ( mark 1 3 1 3 o ) ( mark 1 2 2 2 x ) ( mark 1 1 2 3 x ) ( mark 1 2 3 2 x ) ( mark 2 3 1 3 o ) ( control xPlayer ) ( mark 1 3 2 2 x ) ( mark 3 3 2 2 x ) ( mark 3 2 3 3 x ) ( mark 2 2 3 3 x ) ( mark 3 1 1 2 o ) ( mark 2 2 2 1 o ) ( mark 3 2 1 1 o ) ( mark 3 3 3 2 o ) ( mark 2 1 1 1 x ) ( mark 2 3 3 2 o ) ( mark 2 2 2 3 o ) ( mark 2 2 3 1 x ) )"
    ],
    "tournamentNameFromHost": ""
}